{
    "Series_100": [
        9.641,
        11.28,
        12.24,
        12.37,
        12.82,
        13.17,
        13.3,
        13.43,
        13.72,
        15.03,
        15.18,
        16.1,
        16.28,
        16.6,
        16.64,
        17.6,
        17.92,
        18.86,
        19.0,
        19.32,
        19.36,
        19.39,
        19.44,
        19.51,
        20.3,
        20.45,
        20.53,
        20.62,
        20.99,
        21.06,
        21.09,
        21.18,
        21.21,
        21.26,
        21.26,
        21.27,
        21.29,
        21.65,
        21.84,
        22.27,
        22.4,
        22.69,
        22.79,
        22.88,
        23.11,
        23.17,
        23.2,
        23.36,
        23.82,
        23.84,
        24.22,
        24.36,
        24.85,
        25.0,
        25.16,
        25.18,
        26.31,
        29.05,
        29.33,
        30.18,
        30.85,
        30.88,
        31.16,
        31.74,
        32.77,
        32.9,
        32.93,
        32.94,
        33.39,
        34.11,
        40.25,
        41.2,
        56.3,
        56.72,
        56.83,
        56.86,
        58.21,
        58.58,
        59.29,
        61.13,
        70.24,
        72.25,
        74.81,
        91.0,
        93.59,
        93.8,
        93.89,
        95.97,
        101.4,
        101.67,
        101.85,
        106.96,
        108.42,
        110.4,
        134.49,
        138.51,
        142.15,
        148.03,
        169.91,
        186.23
    ],
    "Dixon_Q": [
        169.91,
        186.23
    ],
    "Standard_Deviation": [
        142.15,
        148.03,
        169.91,
        186.23
    ],
    "Isolation_Forest": [
        9.641,
        11.28,
        34.11,
        40.25,
        41.2,
        56.3,
        56.72,
        58.21,
        58.58,
        59.29,
        61.13,
        70.24,
        72.25,
        74.81,
        91.0,
        93.59,
        93.8,
        93.89,
        95.97,
        101.4,
        101.67,
        101.85,
        106.96,
        108.42,
        110.4,
        134.49,
        138.51,
        142.15,
        148.03,
        169.91,
        186.23
    ],
    "Boxplots": [
        134.49,
        138.51,
        142.15,
        148.03,
        169.91,
        186.23
    ],
    "DBSCAN_Clustering": [
        9.641,
        11.28,
        26.31,
        30.18,
        31.74,
        34.11,
        40.25,
        41.2,
        59.29,
        61.13,
        70.24,
        72.25,
        74.81,
        91.0,
        95.97,
        106.96,
        108.42,
        110.4,
        134.49,
        138.51,
        142.15,
        148.03,
        169.91,
        186.23
    ],
    "Joint_Outliers": [
        169.91,
        186.23
    ],
    "Joint_Outliers_DQ_StD": [
        169.91,
        186.23
    ],
    "Joint_Outliers_DQ_IF": [
        169.91,
        186.23
    ],
    "Joint_Outliers_DQ_BXPLTS": [
        169.91,
        186.23
    ],
    "Joint_Outliers_DQ_DBSCAN_CL": [
        169.91,
        186.23
    ],
    "Joint_Outliers_StD_IF": [
        169.91,
        186.23,
        148.03,
        142.15
    ],
    "Joint_Outliers_StD_BXPLTS": [
        169.91,
        186.23,
        148.03,
        142.15
    ],
    "Joint_Outliers_StD_DBSCAN_CL": [
        169.91,
        186.23,
        148.03,
        142.15
    ],
    "Joint_Outliers_IF_BXPLTS": [
        134.49,
        169.91,
        138.51,
        142.15,
        148.03,
        186.23
    ],
    "Joint_Outliers_IF_DBSCAN_CL": [
        134.49,
        9.641,
        138.51,
        11.28,
        142.15,
        148.03,
        34.11,
        40.25,
        41.2,
        169.91,
        186.23,
        59.29,
        61.13,
        70.24,
        72.25,
        74.81,
        91.0,
        95.97,
        106.96,
        108.42,
        110.4
    ],
    "Joint_Outliers_BXPLTS_DBSCAN_CL": [
        134.49,
        169.91,
        138.51,
        142.15,
        148.03,
        186.23
    ]
}